kafka_manager/__init__.py
kafka_manager/__version__.py
kafka_manager/kafka_consumer_client.py
kafka_manager/kafka_manager.py
kafka_manager/kafka_producer_client.py
kafka_manager-0.0.3.dist-info/licenses/LICENSE
kafka_manager-0.0.3.dist-info/METADATA
kafka_manager-0.0.3.dist-info/WHEEL
kafka_manager-0.0.3.dist-info/top_level.txt
kafka_manager-0.0.3.dist-info/RECORD
